spestimator/__init__.py
spestimator/cli.py
spestimator/database.py
spestimator/estimation.py
spestimator/genome.py
spestimator/metadata.py
spestimator/data/bacteria.16SrRNA.ndb
spestimator/data/bacteria.16SrRNA.nhr
spestimator/data/bacteria.16SrRNA.nin
spestimator/data/bacteria.16SrRNA.nog
spestimator/data/bacteria.16SrRNA.nos
spestimator/data/bacteria.16SrRNA.not
spestimator/data/bacteria.16SrRNA.nsq
spestimator/data/bacteria.16SrRNA.ntf
spestimator/data/bacteria.16SrRNA.nto
spestimator/data/metadata.csv.gz
spestimator-0.1.0.232.dist-info/licenses/LICENSE
spestimator-0.1.0.232.dist-info/METADATA
spestimator-0.1.0.232.dist-info/WHEEL
spestimator-0.1.0.232.dist-info/entry_points.txt
spestimator-0.1.0.232.dist-info/top_level.txt
spestimator-0.1.0.232.dist-info/RECORD
