Metadata-Version: 2.4
Name: spestimator
Version: 0.1.0.232
Summary: A tool to predict bacterial species from fasta files using RefSeq 16S.
Author-email: Erin Young <eriny@utah.gov>
License: MIT License
Project-URL: Homepage, https://github.com/erinyoung/Spestimator
Classifier: Programming Language :: Python :: 3
Classifier: Operating System :: OS Independent
Requires-Python: >=3.9
License-File: LICENSE
Requires-Dist: pandas
Requires-Dist: requests
Requires-Dist: tqdm
Requires-Dist: ncbi-datasets-pyclient
Provides-Extra: dev
Requires-Dist: pytest; extra == "dev"
Requires-Dist: pytest-cov; extra == "dev"
Requires-Dist: build; extra == "dev"
Requires-Dist: twine; extra == "dev"
Dynamic: license-file
